toolregistry_hub/__init__.py
toolregistry_hub/calculator.py
toolregistry_hub/datetime_utils.py
toolregistry_hub/fetch.py
toolregistry_hub/file_ops.py
toolregistry_hub/filesystem.py
toolregistry_hub/py.typed
toolregistry_hub/think_tool.py
toolregistry_hub/todo_list.py
toolregistry_hub/unit_converter.py
toolregistry_hub/version_check.py
toolregistry_hub/server/__init__.py
toolregistry_hub/server/auth.py
toolregistry_hub/server/banner.py
toolregistry_hub/server/cli.py
toolregistry_hub/server/server_core.py
toolregistry_hub/server/server_mcp.py
toolregistry_hub/server/server_openapi.py
toolregistry_hub/server/routes/__init__.py
toolregistry_hub/server/routes/calculator.py
toolregistry_hub/server/routes/datetime_tools.py
toolregistry_hub/server/routes/fetch.py
toolregistry_hub/server/routes/think.py
toolregistry_hub/server/routes/todo_list.py
toolregistry_hub/server/routes/unit_converter.py
toolregistry_hub/server/routes/version.py
toolregistry_hub/server/routes/deprecated/bing.py
toolregistry_hub/server/routes/websearch/__init__.py
toolregistry_hub/server/routes/websearch/brave.py
toolregistry_hub/server/routes/websearch/brightdata.py
toolregistry_hub/server/routes/websearch/models.py
toolregistry_hub/server/routes/websearch/scrapeless.py
toolregistry_hub/server/routes/websearch/searxng.py
toolregistry_hub/server/routes/websearch/tavily.py
toolregistry_hub/utils/__init__.py
toolregistry_hub/utils/api_key_parser.py
toolregistry_hub/utils/fn_namespace.py
toolregistry_hub/websearch/__init__.py
toolregistry_hub/websearch/base.py
toolregistry_hub/websearch/google_parser.py
toolregistry_hub/websearch/search_result.py
toolregistry_hub/websearch/websearch_bing.py
toolregistry_hub/websearch/websearch_brave.py
toolregistry_hub/websearch/websearch_brightdata.py
toolregistry_hub/websearch/websearch_scrapeless.py
toolregistry_hub/websearch/websearch_searxng.py
toolregistry_hub/websearch/websearch_tavily.py
toolregistry_hub/websearch_legacy/__init__.py
toolregistry_hub-0.5.5.dist-info/licenses/LICENSE
toolregistry_hub-0.5.5.dist-info/METADATA
toolregistry_hub-0.5.5.dist-info/WHEEL
toolregistry_hub-0.5.5.dist-info/entry_points.txt
toolregistry_hub-0.5.5.dist-info/top_level.txt
toolregistry_hub-0.5.5.dist-info/RECORD
