Metadata-Version: 2.4
Name: toolregistry-hub
Version: 0.5.5
Summary: ToolRegistry Hub: A Python library providing various utility tools for mathematical calculations, date/time operations, file management, web search, unit conversions, and more - designed to support common tasks in LLM function calling and general development
Author-email: Oaklight <oaklight@gmx.com>
License: MIT
Project-URL: Documentation, https://toolregistry.readthedocs.io
Project-URL: Repository, https://github.com/Oaklight/toolregistry-hub
Project-URL: Issues, https://github.com/Oaklight/toolregistry-hub/issues
Classifier: Intended Audience :: Developers
Classifier: Programming Language :: Python :: 3
Classifier: Topic :: Software Development :: Libraries :: Python Modules
Classifier: Topic :: Scientific/Engineering :: Artificial Intelligence
Requires-Python: >=3.8
License-File: LICENSE
Requires-Dist: loguru>=0.7.3
Requires-Dist: httpx>=0.28.1
Requires-Dist: ua-generator>=1.0.6; python_version < "3.9"
Requires-Dist: ua-generator
Requires-Dist: beautifulsoup4>=4.13.4
Requires-Dist: pydantic<3.0.0,>=2.7.2
Requires-Dist: backports.zoneinfo>=0.2.1; python_version < "3.9"
Provides-Extra: dev
Requires-Dist: python-dotenv>=1.0.1; extra == "dev"
Requires-Dist: pyright>=1.1.402; extra == "dev"
Requires-Dist: build>=1.2.2.post1; extra == "dev"
Requires-Dist: twine>=6.1.0; extra == "dev"
Requires-Dist: pytest>=7.0.0; extra == "dev"
Provides-Extra: server-openapi
Requires-Dist: fastapi>=0.119.0; extra == "server-openapi"
Requires-Dist: uvicorn[standard]>=0.24.0; extra == "server-openapi"
Provides-Extra: server-mcp
Requires-Dist: fastapi>=0.119.0; extra == "server-mcp"
Requires-Dist: fastmcp>=2.12.4; python_version >= "3.10" and extra == "server-mcp"
Provides-Extra: server
Requires-Dist: fastapi>=0.119.0; extra == "server"
Requires-Dist: uvicorn[standard]>=0.24.0; extra == "server"
Requires-Dist: fastmcp>=2.12.4; python_version >= "3.10" and extra == "server"
Dynamic: license-file
